noteable/__init__.py
noteable/hello.py
noteable-0.0.1.dist-info/METADATA
noteable-0.0.1.dist-info/WHEEL
noteable-0.0.1.dist-info/top_level.txt
noteable-0.0.1.dist-info/RECORD
