Metadata-Version: 2.1
Name: noteable
Version: 0.0.1
Summary: Noteable public packages
Home-page: UNKNOWN
Author: Noteable Inc
Author-email: os@noteable.io
License: BSD
Keywords: notebook
Platform: UNKNOWN
Classifier: Intended Audience :: Developers
Classifier: License :: OSI Approved :: BSD License
Classifier: Programming Language :: Python
Classifier: Programming Language :: Python :: 3
Requires-Python: >=3.6
